MANIFEST.in
README.rst
setup.py
django_linkthru.egg-info/PKG-INFO
django_linkthru.egg-info/SOURCES.txt
django_linkthru.egg-info/dependency_links.txt
django_linkthru.egg-info/requires.txt
django_linkthru.egg-info/top_level.txt
django_linkthru.egg-info/zip-safe
linkthru/__init__.py
linkthru/admin.py
linkthru/context_processors.py
linkthru/managers.py
linkthru/models.py
linkthru/tests.py
linkthru/urls.py
linkthru/views.py
linkthru/templates/linkthru/link_tag.html
linkthru/templates/linkthru/link_tag_block.html
linkthru/templatetags/__init__.py
linkthru/templatetags/linkthru_tags.py