Metadata-Version: 1.0
Name: django-linkthru
Version: 0.2.1
Summary: A riff on adzone, but without the advert cruft. Just text/images linking to arbitrary urls.
Home-page: http://github.com/powellc/django-linkthru
Author: Colin Powell
Author-email: colin@onecardinal.com
License: GPLv3
Download-URL: http://github.com/powellc/django-linkthru/downloads
Platform: UNKNOWN
Classifier: Development Status :: 4 - Beta
Classifier: Environment :: Web Environment
Classifier: Intended Audience :: Developers
Classifier: License :: OSI Approved :: BSD License
Classifier: Operating System :: OS Independent
Classifier: Programming Language :: Python
Classifier: Framework :: Django
